poppy/__init__.py
poppy/bootstrap.py
poppy/version.py
poppy/cmd/__init__.py
poppy/cmd/akamai_check_and_update_cert_status.py
poppy/cmd/akamai_update_papi_property_for_mod_san.py
poppy/cmd/delete_obsolete_http_policies.py
poppy/cmd/server.py
poppy/cmd/task_flow_worker.py
poppy/common/__init__.py
poppy/common/_i18n.py
poppy/common/cli.py
poppy/common/decorators.py
poppy/common/errors.py
poppy/common/uri.py
poppy/common/util.py
poppy/distributed_task/__init__.py
poppy/distributed_task/base/__init__.py
poppy/distributed_task/base/controller.py
poppy/distributed_task/base/driver.py
poppy/distributed_task/base/services.py
poppy/distributed_task/taskflow/__init__.py
poppy/distributed_task/taskflow/controllers.py
poppy/distributed_task/taskflow/driver.py
poppy/distributed_task/taskflow/services.py
poppy/distributed_task/taskflow/flow/__init__.py
poppy/distributed_task/taskflow/flow/create_service.py
poppy/distributed_task/taskflow/flow/create_ssl_certificate.py
poppy/distributed_task/taskflow/flow/delete_service.py
poppy/distributed_task/taskflow/flow/delete_ssl_certificate.py
poppy/distributed_task/taskflow/flow/purge_service.py
poppy/distributed_task/taskflow/flow/recreate_ssl_certificate.py
poppy/distributed_task/taskflow/flow/update_service.py
poppy/distributed_task/taskflow/flow/update_service_state.py
poppy/distributed_task/taskflow/task/__init__.py
poppy/distributed_task/taskflow/task/common.py
poppy/distributed_task/taskflow/task/create_service_tasks.py
poppy/distributed_task/taskflow/task/create_ssl_certificate_tasks.py
poppy/distributed_task/taskflow/task/delete_service_tasks.py
poppy/distributed_task/taskflow/task/delete_ssl_certificate_tasks.py
poppy/distributed_task/taskflow/task/purge_service_tasks.py
poppy/distributed_task/taskflow/task/update_service_state_tasks.py
poppy/distributed_task/taskflow/task/update_service_tasks.py
poppy/distributed_task/utils/__init__.py
poppycdn-1.0.13.dist-info/DESCRIPTION.rst
poppycdn-1.0.13.dist-info/METADATA
poppycdn-1.0.13.dist-info/RECORD
poppycdn-1.0.13.dist-info/WHEEL
poppycdn-1.0.13.dist-info/entry_points.txt
poppycdn-1.0.13.dist-info/metadata.json
poppycdn-1.0.13.dist-info/pbr.json
poppycdn-1.0.13.dist-info/top_level.txt
