Metadata-Version: 2.0
Name: poppycdn
Version: 1.0.13
Summary: A modular, vendor-neutral API, that wraps provisioning instructions for all CDN vendors that support it.
Home-page: http://www.openstack.org/
Author: OpenStack
Author-email: openstack-dev@lists.openstack.org
License: UNKNOWN
Platform: UNKNOWN
Classifier: Environment :: OpenStack
Classifier: Intended Audience :: Information Technology
Classifier: Intended Audience :: System Administrators
Classifier: License :: OSI Approved :: Apache Software License
Classifier: Operating System :: POSIX :: Linux
Classifier: Programming Language :: Python
Classifier: Programming Language :: Python :: 2
Classifier: Programming Language :: Python :: 2.7
Requires-Dist: oslo.utils (>=2.0.0)
Requires-Dist: httplib2 (>=0.8)
Requires-Dist: oslo.log (>=1.12.1)
Requires-Dist: sphinxcontrib-httpdomain
Requires-Dist: netifaces (>=0.10.4)
Requires-Dist: WebOb (>=1.2.3,<1.3)
Requires-Dist: sphinxcontrib-pecanwsme
Requires-Dist: oslo.i18n (>=2.1.0)
Requires-Dist: netaddr (>=0.7.6)
Requires-Dist: pyrax
Requires-Dist: python-keystoneclient (>=0.4.1)
Requires-Dist: requests-futures
Requires-Dist: boto (>=2.31.1)
Requires-Dist: oslosphinx
Requires-Dist: oslo.config (>=2.0.0)
Requires-Dist: cassandra-driver (>=3.0.0)
Requires-Dist: dnspython (>=1.14.0)
Requires-Dist: sphinx
Requires-Dist: python-whois (>=0.6.2)
Requires-Dist: pecan (>=0.8.1)
Requires-Dist: maxcdn
Requires-Dist: pbr (==0.11.0)
Requires-Dist: cdn-fastly (==1.0.4)
Requires-Dist: taskflow
Requires-Dist: jsonschema (>=1.3.0,!=1.4.0)
Requires-Dist: stevedore (>=0.10)
Requires-Dist: tld (>=0.7.6)
Requires-Dist: kazoo
Requires-Dist: zake
Requires-Dist: msgpack-python
Requires-Dist: jsonpatch
Requires-Dist: oslo.serialization (>=1.7.0)
Requires-Dist: ordereddict
Requires-Dist: certifi (==2015.4.28)
Requires-Dist: cdeploy
Requires-Dist: six (>=1.4.1)
Requires-Dist: pyOpenSSL
Requires-Dist: edgegrid-python (==1.0.6)
Requires-Dist: SecretStorage (==2.1.4)
Requires-Dist: pymongo (>=2.4)
Requires-Dist: iso8601 (>=0.1.8)
Requires-Dist: Babel (>=1.3)
